.gitignore
.gitmodules
AUTHORS.md
INSTALL.md
LICENSE.txt
MANIFEST.in
README.md
example-test-file.txt
pytest.ini
requirements.txt
setup.cfg
setup.py
test-requirements.txt
estimatecharm/Makefile
estimatecharm/__init__.py
estimatecharm/estimateCharm.py
estimatecharm/flexibleTokenize.py
estimatecharm/pythonSource.py
estimatecharm/ucTestData.py
estimatecharm/unnaturalCode.py
estimatecharm.egg-info/PKG-INFO
estimatecharm.egg-info/SOURCES.txt
estimatecharm.egg-info/dependency_links.txt
estimatecharm.egg-info/entry_points.txt
estimatecharm.egg-info/not-zip-safe
estimatecharm.egg-info/top_level.txt
tests/testPythonLexical.py
tests/testUnnaturalCodePython.py