Metadata-Version: 1.1
Name: estimatecharm
Version: 0.1
Summary: Code Charm Estimation Tool
Home-page: https://github.com/orezpraw/estimate-charm
Author: Joshua Charles Campbell
Author-email: joshua2@ualberta.ca
License: AGPL3+
Download-URL: https://github.com/orezpraw/estimate-charm/tarball/0.1
Platform: UNKNOWN
